README.rst
setup.py
find_japanese/__init__.py
find_japanese/find_japanese.py
find_japanese.egg-info/PKG-INFO
find_japanese.egg-info/SOURCES.txt
find_japanese.egg-info/dependency_links.txt
find_japanese.egg-info/not-zip-safe
find_japanese.egg-info/requires.txt
find_japanese.egg-info/top_level.txt