Metadata-Version: 1.1
Name: find-japanese
Version: 0.0.1
Summary: This is a find find_japanese
Home-page: http://satoshun.github.com/
Author: Sato Shun
Author-email: shun.sato1@gmail.com
License: Apache License, Version 2.0
Keywords: japanese,regular expression
Platform: UNKNOWN
Classifier: Programming Language :: Python :: 3
Classifier: Programming Language :: Python :: 3.2
Classifier: Programming Language :: Python :: 3.3
